bokkichat/__init__.py
bokkichat/exceptions.py
bokkichat/connection/Connection.py
bokkichat/connection/__init__.py
bokkichat/connection/impl/CliConnection.py
bokkichat/connection/impl/TelegramBotConnection.py
bokkichat/connection/impl/__init__.py
bokkichat/entities/Address.py
bokkichat/entities/__init__.py
bokkichat/entities/message/MediaMessage.py
bokkichat/entities/message/MediaType.py
bokkichat/entities/message/Message.py
bokkichat/entities/message/TextMessage.py
bokkichat/entities/message/__init__.py
bokkichat/settings/Settings.py
bokkichat/settings/__init__.py
bokkichat/settings/impl/CliSettings.py
bokkichat/settings/impl/TelegramBotSettings.py
bokkichat/settings/impl/__init__.py
bokkichat/test/__init__.py
bokkichat-0.4.5.data/scripts/bokkichat-cli
bokkichat-0.4.5.data/scripts/telegram-bot-cli
bokkichat-0.4.5.dist-info/LICENSE
bokkichat-0.4.5.dist-info/METADATA
bokkichat-0.4.5.dist-info/WHEEL
bokkichat-0.4.5.dist-info/top_level.txt
bokkichat-0.4.5.dist-info/RECORD
