Metadata-Version: 2.1
Name: bokkichat
Version: 0.4.5
Summary: A python library for various chat services
Home-page: https://gitlab.namibsun.net/namibsun/python/bokkichat
Author: Hermann Krumrey
Author-email: hermann@krumreyh.com
License: GNU GPL3
Platform: UNKNOWN
Classifier: License :: OSI Approved :: GNU General Public License v3 (GPLv3)
License-File: LICENSE
Requires-Dist: python-telegram-bot
Requires-Dist: requests
